daphne/__init__.py
daphne/__main__.py
daphne/access.py
daphne/apps.py
daphne/checks.py
daphne/cli.py
daphne/endpoints.py
daphne/http_protocol.py
daphne/server.py
daphne/testing.py
daphne/utils.py
daphne/ws_protocol.py
twisted/plugins/fd_endpoint.py
daphne-4.1.1.dist-info/LICENSE
daphne-4.1.1.dist-info/METADATA
daphne-4.1.1.dist-info/WHEEL
daphne-4.1.1.dist-info/entry_points.txt
daphne-4.1.1.dist-info/top_level.txt
daphne-4.1.1.dist-info/RECORD
