Metadata-Version: 2.1
Name: daphne
Version: 4.1.1
Summary: Django ASGI (HTTP/WebSocket) server
Home-page: https://github.com/django/daphne
Author: Django Software Foundation
Author-email: foundation@djangoproject.com
License: BSD
Classifier: Development Status :: 4 - Beta
Classifier: Environment :: Web Environment
Classifier: Intended Audience :: Developers
Classifier: License :: OSI Approved :: BSD License
Classifier: Operating System :: OS Independent
Classifier: Programming Language :: Python
Classifier: Programming Language :: Python :: 3
Classifier: Programming Language :: Python :: 3.8
Classifier: Programming Language :: Python :: 3.9
Classifier: Programming Language :: Python :: 3.10
Classifier: Programming Language :: Python :: 3.11
Classifier: Programming Language :: Python :: 3.12
Classifier: Topic :: Internet :: WWW/HTTP
Requires-Python: >=3.8
License-File: LICENSE
Requires-Dist: asgiref <4,>=3.5.2
Requires-Dist: autobahn >=22.4.2
Requires-Dist: twisted[tls] >=22.4
Provides-Extra: tests
Requires-Dist: django ; extra == 'tests'
Requires-Dist: hypothesis ; extra == 'tests'
Requires-Dist: pytest ; extra == 'tests'
Requires-Dist: pytest-asyncio ; extra == 'tests'
